ipycollections/__init__.py
ipycollections/_version.py
ipycollections/formatter.py
ipycollections/printer.py
ipycollections-0.4.0.data/data/share/jupyter/labextensions/@dfnotebook/ipycollections-extension/package.json
ipycollections-0.4.0.data/data/share/jupyter/labextensions/@dfnotebook/ipycollections-extension/static/237.53b46a99a955eebbe921.js
ipycollections-0.4.0.data/data/share/jupyter/labextensions/@dfnotebook/ipycollections-extension/static/747.4719eeedef9cb479dc2c.js
ipycollections-0.4.0.data/data/share/jupyter/labextensions/@dfnotebook/ipycollections-extension/static/remoteEntry.deff0edfc85657330195.js
ipycollections-0.4.0.data/data/share/jupyter/labextensions/@dfnotebook/ipycollections-extension/static/style.js
ipycollections-0.4.0.data/data/share/jupyter/labextensions/@dfnotebook/ipycollections-extension/static/third-party-licenses.json
ipycollections-0.4.0.data/data/share/jupyter/labextensions/@dfnotebook/ipycollections-extension/install.json
ipycollections-0.4.0.dist-info/METADATA
ipycollections-0.4.0.dist-info/WHEEL
ipycollections-0.4.0.dist-info/licenses/LICENSE
ipycollections-0.4.0.dist-info/RECORD
