Metadata-Version: 2.1
Name: ipycollections
Version: 0.4.0
Summary: A JupyterLab extension that provides a more interactive format for collections
Project-URL: Homepage, https://github.com/dataflownb/ipycollections-extension
Project-URL: Bug Tracker, https://github.com/dataflownb/ipycollections-extension/issues
Project-URL: Repository, https://github.com/dataflownb/ipycollections-extension.git
Author-email: David Koop <dakoop@niu.edu>
License: BSD 3-Clause License
License-File: LICENSE
Classifier: Framework :: Jupyter
Classifier: Framework :: Jupyter :: JupyterLab
Classifier: Framework :: Jupyter :: JupyterLab :: 4
Classifier: Framework :: Jupyter :: JupyterLab :: Extensions
Classifier: Framework :: Jupyter :: JupyterLab :: Extensions :: Prebuilt
Classifier: License :: OSI Approved :: BSD License
Classifier: Programming Language :: Python
Classifier: Programming Language :: Python :: 3
Classifier: Programming Language :: Python :: 3.8
Classifier: Programming Language :: Python :: 3.9
Classifier: Programming Language :: Python :: 3.10
Classifier: Programming Language :: Python :: 3.11
Classifier: Programming Language :: Python :: 3.12
Requires-Python: >=3.8
